minecart/__init__.py
minecart/color.py
minecart/content.py
minecart/miner.py
minecart-0.3.0.dist-info/DESCRIPTION.rst
minecart-0.3.0.dist-info/METADATA
minecart-0.3.0.dist-info/RECORD
minecart-0.3.0.dist-info/WHEEL
minecart-0.3.0.dist-info/metadata.json
minecart-0.3.0.dist-info/top_level.txt
