Metadata-Version: 1.1
Name: minecart
Version: 0.3.0
Summary: Simple, Pythonic extraction of images, text, and shapes from PDFs
Home-page: https://github.com/felipeochoa/minecart
Author: Felipe Ochoa
Author-email: felipeochoa@github.com
License: MIT
Download-URL: https://github.com/felipeochoa/minecart/tarball/0.3.0
Keywords: pdf pdfminer extract mining images
Platform: UNKNOWN
Classifier: Development Status :: 4 - Beta
Classifier: Intended Audience :: Developers
Classifier: Operating System :: OS Independent
Classifier: Programming Language :: Python :: 3.5
Classifier: Programming Language :: Python :: 3.6
Classifier: Programming Language :: Python :: 3 :: Only
Classifier: License :: OSI Approved :: MIT License
